izanami/__init__.py
izanami/controller.py
izanami/forms.py
izanami/gitHttpBackend.py
izanami/main.py
izanami/model.py
izanami/static/highlight/a11y-dark.css
izanami/static/highlight/a11y-light.css
izanami/static/highlight/agate.css
izanami/static/highlight/an-old-hope.css
izanami/static/highlight/androidstudio.css
izanami/static/highlight/arduino-light.css
izanami/static/highlight/arta.css
izanami/static/highlight/ascetic.css
izanami/static/highlight/atelier-cave-dark.css
izanami/static/highlight/atelier-cave-light.css
izanami/static/highlight/atelier-dune-dark.css
izanami/static/highlight/atelier-dune-light.css
izanami/static/highlight/atelier-estuary-dark.css
izanami/static/highlight/atelier-estuary-light.css
izanami/static/highlight/atelier-forest-dark.css
izanami/static/highlight/atelier-forest-light.css
izanami/static/highlight/atelier-heath-dark.css
izanami/static/highlight/atelier-heath-light.css
izanami/static/highlight/atelier-lakeside-dark.css
izanami/static/highlight/atelier-lakeside-light.css
izanami/static/highlight/atelier-plateau-dark.css
izanami/static/highlight/atelier-plateau-light.css
izanami/static/highlight/atelier-savanna-dark.css
izanami/static/highlight/atelier-savanna-light.css
izanami/static/highlight/atelier-seaside-dark.css
izanami/static/highlight/atelier-seaside-light.css
izanami/static/highlight/atelier-sulphurpool-dark.css
izanami/static/highlight/atelier-sulphurpool-light.css
izanami/static/highlight/atom-one-dark-reasonable.css
izanami/static/highlight/atom-one-dark.css
izanami/static/highlight/atom-one-light.css
izanami/static/highlight/brown-paper.css
izanami/static/highlight/brown-papersq.png
izanami/static/highlight/codepen-embed.css
izanami/static/highlight/color-brewer.css
izanami/static/highlight/darcula.css
izanami/static/highlight/dark.css
izanami/static/highlight/default.css
izanami/static/highlight/docco.css
izanami/static/highlight/dracula.css
izanami/static/highlight/far.css
izanami/static/highlight/foundation.css
izanami-1.1.10.dist-info/WHEEL
izanami-1.1.10.dist-info/METADATA
izanami-1.1.10.dist-info/RECORD
