Metadata-Version: 2.1
Name: izanami
Version: 1.1.10
Summary: 
License: MIT
Author: boke0
Author-email: speken00.tt@gmail.com
Requires-Python: >=3.6,<4.0
Classifier: License :: OSI Approved :: MIT License
Classifier: Programming Language :: Python :: 3
Classifier: Programming Language :: Python :: 3.6
Classifier: Programming Language :: Python :: 3.7
Classifier: Programming Language :: Python :: 3.8
Classifier: Programming Language :: Python :: 3.9
Requires-Dist: GitPython (>=3.1.13,<4.0.0)
Requires-Dist: PyYAML (>=5.4.1,<6.0.0)
Requires-Dist: docker (>=4.4.4,<5.0.0)
Requires-Dist: unidiff (>=0.6.0,<0.7.0)
